{
  "sector1": {
    "caracterObjetivos": "<strong>Carácter y objetivos</strong><br/> Es un curso de Mecánica Clásica de primer nivel que básicamente estudia: mecánica del punto, mecánica del cuerpo rígido y movimiento oscilatorio, con uno y dos grados de libertad, mecánica de fluidos y transferencia de calor.<br/> El curso está dirigido a estudiantes de todas las carreras buscando destacar la relación de la Física y en especial de la Mecánica con la Química y con aplicaciones en general. Al mismo tiempo se busca mostrar como varios conceptos con origen en Mecánica Clásica, han sido extendidos luego a otras áreas de la Física o a las demás Ciencias.<br/> El Curso busca darle al estudiante un manejo sólido del método científico, junto con un espíritu crítico muy desarrollado. Desde el punto de vista técnico se procura familiarizar al estudiante con los Principios de Conservación de Energía y Cantidad de Movimiento Lineal y Angular. Se busca que el estudiante aprenda a transformar una situación física en un problema matemático a resolver y estudiar luego el carácter de la solución obtenida.",
    "comienzo": {
      "fecha": "",
      "teorico": {
        "dias": "",
        "lugar": ""
      },
      "practico": "",
      "talleres": "",
      "consultas": {
        "horario": "",
        "lugar": ""
      }
    }
  },
  "sector2": {
    "horarios": {
      "src": "",
      "title": "Horarios",
      "alt": "Imagen de los horarios"
    },
    "talleres": {
      "informacion": {
        "obligatoriedad": "",
        "presencialidad": "",
        "totalTalleres": "",
        "GananciaEvaluacion": "",
        "puntajeMaximo": ""
      },
      "grupos": {
        "grupo1": {
          "dia": "",
          "horario": "",
          "lugar": ""
        },
        "grupo2": {
          "dia": "",
          "horario": "",
          "lugar": ""
        },
        "grupo3": {
          "dia": "",
          "horario": "",
          "lugar": ""
        },
        "grupo4": {
          "dia": "",
          "horario": "",
          "lugar": ""
        },
        "grupo5": {
          "dia": "",
          "horario": "",
          "lugar": ""
        }
      }
    },
    "cronograma": {
      "src": "",
      "title": "Cronograma",
      "alt": "Imagen del cronograma"
    }
  },
  "sector3": {
    "descargables": {
      "informacionCurso": {
        "titulo": "",
        "programa": {
          "label": "",
          "src": ""
        },
        "estructura": {
          "label": "",
          "src": ""
        }
      },
      "materiales": {
        "titulo": "",
        "libro": {
          "label": "",
          "src": ""
        },
        "formulas": {
          "label": "",
          "src": ""
        }
      },
      "simulaciones": {
        "web1": {
          "src": ""
        },
        "web2": {
          "src": ""
        }
      }
    },
    "cartelera": {}
  }
}
